{
  "name": "breadcrumbs-basic",
  "type": "registry:demo",
  "registryDependencies": [
    "breadcrumbs"
  ],
  "files": [
    {
      "path": "core/breadcrumbs/demos/basic.tsx",
      "content": "import {\n  Breadcrumbs,\n  Breadcrumb,\n} from \"@/registry/ui/default/core/breadcrumbs\";\n\nexport default function Demo() {\n  return (\n    <Breadcrumbs>\n      <Breadcrumb href=\"#\">Home</Breadcrumb>\n      <Breadcrumb href=\"#\">Components</Breadcrumb>\n      <Breadcrumb href=\"#\">Breadcrumbs</Breadcrumb>\n    </Breadcrumbs>\n  );\n}\n",
      "type": "registry:demo",
      "target": ""
    }
  ]
}