{
  "name": "color-picker-composition",
  "type": "registry:demo",
  "registryDependencies": [
    "color-picker"
  ],
  "files": [
    {
      "path": "core/color-picker/demos/composition.tsx",
      "content": "import { Button } from \"@/registry/ui/default/core/button\";\r\nimport {\r\n  ColorEditor,\r\n  ColorPickerRoot,\r\n} from \"@/registry/ui/default/core/color-picker\";\r\nimport { ColorSwatch } from \"@/registry/ui/default/core/color-swatch\";\r\nimport { Dialog, DialogRoot } from \"@/registry/ui/default/core/dialog\";\r\n\r\nexport default function Demo() {\r\n  return (\r\n    <ColorPickerRoot defaultValue=\"#5100FF\">\r\n      <DialogRoot>\r\n        <Button shape=\"square\">\r\n          <ColorSwatch />\r\n        </Button>\r\n        <Dialog type=\"popover\" mobileType=\"drawer\">\r\n          <ColorEditor />\r\n        </Dialog>\r\n      </DialogRoot>\r\n    </ColorPickerRoot>\r\n  );\r\n}\r\n",
      "type": "registry:demo",
      "target": ""
    }
  ]
}