{
  "name": "date-field-composition",
  "type": "registry:demo",
  "registryDependencies": [
    "date-field"
  ],
  "files": [
    {
      "path": "core/date-field/demos/composition.tsx",
      "content": "\"use client\";\n\nimport React from \"react\";\nimport { DateFieldRoot } from \"@/registry/ui/default/core/date-field\";\nimport { DateInput, DateSegment } from \"@/registry/ui/default/core/date-input\";\nimport { Description, Label } from \"@/registry/ui/default/core/field\";\nimport { InputRoot } from \"@/registry/ui/default/core/input\";\n\nexport default function Demo() {\n  return (\n    <DateFieldRoot>\n      <Label>Meeting time</Label>\n      <InputRoot>\n        <DateInput>{(segment) => <DateSegment segment={segment} />}</DateInput>\n      </InputRoot>\n      <Description>Please select a time between 9 AM and 5 PM.</Description>\n    </DateFieldRoot>\n  );\n}\n",
      "type": "registry:demo",
      "target": ""
    }
  ]
}